cmditch_pyscip_test-0.1.1.dist-info/WHEEL
cmditch_pyscip_test-0.1.1.dist-info/LICENSE
cmditch_pyscip_test-0.1.1.dist-info/METADATA
cmditch_pyscip_test-0.1.1.dist-info/top_level.txt
cmditch_pyscip_test-0.1.1.dist-info/RECORD
pyscipopt/presol.pxi
pyscipopt/benderscut.pxi
pyscipopt/scip.pxi
pyscipopt/_version.py
pyscipopt/pricer.pxi
pyscipopt/conshdlr.pxi
pyscipopt/scip.cpython-39-x86_64-linux-gnu.so
pyscipopt/event.pxi
pyscipopt/relax.pxi
pyscipopt/__init__.py
pyscipopt/heuristic.pxi
pyscipopt/lp.pxi
pyscipopt/Multidict.py
pyscipopt/scip.pyx
pyscipopt/branchrule.pxi
pyscipopt/nodesel.pxi
pyscipopt/reader.pxi
pyscipopt/cutsel.pxi
pyscipopt/propagator.pxi
pyscipopt/expr.pxi
pyscipopt/benders.pxi
pyscipopt/scip.pxd
pyscipopt/sepa.pxi
pyscipopt/recipes/infeasibilities.py
pyscipopt/recipes/__init__.py
pyscipopt/recipes/nonlinear.py
pyscipopt/recipes/piecewise.py
cmditch_pyscip_test.libs/libscip-26410fff.so.9.1
cmditch_pyscip_test.libs/libgfortran-93980b03.so.5.0.0
cmditch_pyscip_test.libs/libquadmath-776d53b6.so.0.0.0
