Metadata-Version: 2.1
Name: cmditch-pyscip-test
Version: 0.1.1
Summary: Test package
Home-page: https://github.com/SCIP-Interfaces/PySCIPOpt
Author: Murray Rothbard
Author-email: Murray Rothbard <murray@mises.ru>
License: MIT
Requires-Python: >=3.8
License-File: LICENSE
